{
  "project_info": {
    "project_number": "888572498233",
    "firebase_url": "https://event-e07a4.firebaseio.com",
    "project_id": "event-e07a4",
    "storage_bucket": "event-e07a4.appspot.com"
  },
  "client": [
    {
      "client_info": {
        "mobilesdk_app_id": "1:888572498233:android:24d42b1b85a114a76818e8",
        "android_client_info": {
          "package_name": "com.example.event"
        }
      },
      "oauth_client": [
        {
          "client_id": "888572498233-5nfqs2sm4au25dfs6uu418mg0ukcnmdj.apps.googleusercontent.com",
          "client_type": 3
        }
      ],
      "api_key": [
        {
          "current_key": "AIzaSyANyPFtyzMZg-So6B0t7URCAUqmi7zpqI8"
        }
      ],
      "services": {
        "appinvite_service": {
          "other_platform_oauth_client": [
            {
              "client_id": "888572498233-5nfqs2sm4au25dfs6uu418mg0ukcnmdj.apps.googleusercontent.com",
              "client_type": 3
            }
          ]
        }
      }
    },
    {
      "client_info": {
        "mobilesdk_app_id": "1:888572498233:android:26c123911603a09d6818e8",
        "android_client_info": {
          "package_name": "com.example.events"
        }
      },
      "oauth_client": [
        {
          "client_id": "888572498233-5nfqs2sm4au25dfs6uu418mg0ukcnmdj.apps.googleusercontent.com",
          "client_type": 3
        }
      ],
      "api_key": [
        {
          "current_key": "AIzaSyANyPFtyzMZg-So6B0t7URCAUqmi7zpqI8"
        }
      ],
      "services": {
        "appinvite_service": {
          "other_platform_oauth_client": [
            {
              "client_id": "888572498233-5nfqs2sm4au25dfs6uu418mg0ukcnmdj.apps.googleusercontent.com",
              "client_type": 3
            }
          ]
        }
      }
    }
  ],
  "configuration_version": "1"
}